[
    {
        "classId": "e_16",
        "classId_name": "其他",
        "text": "## 格力+隐私政策\n本政策仅适用于珠海格力电器股份有限公司的格力+App提供的产品或服务，包括您访问格力+App使用平台提供的服务。 版本生效日期：2020年6月30日\n最近更新日期：2020年6月30日",
        "start": 40,
        "end": 143,
        "fields": [],
        "sub_annotations": []
    },
    {
        "classId": "e_16",
        "classId_name": "其他",
        "text": "本政策将帮助您了解以下内容： 一、我们如何收集和使用您的个人信息 二、我们如何共享、转让、公开披露您的个人信息\n三、我们如何保护您的个人信息 四、我们如何处理儿童的个人信息 五、我们如何使用 Cookie 和同类技术 六、您的权利\n七、您的个人信息如何储存及超出储存期限处理办法 八、本政策如何更新 九、如何联系我们",
        "start": 156,
        "end": 314,
        "fields": [],
        "sub_annotations": []
    },
    {
        "classId": "e_16",
        "classId_name": "其他",
        "text": "格力深知个人信息对您的重要性，并会尽全力保护您的个人信息安全可靠。我们致力于维持您对我们的信任，恪守以下原则，保护您的个人信息：权责一致原则、目的明确原则、选择同意原则、最少够用原则、确保安全原则、主体参与原则、公开透明原则。同时，格力承诺，我们将按业界成熟的安全标准，采取相应的安全保护措施来保护您的个人信息。请在使用我们的产品（或服务）前，仔细阅读并了解本《隐私政策》。",
        "start": 326,
        "end": 513,
        "fields": [],
        "sub_annotations": []
    },
    {
        "classId": "e_1",
        "classId_name": "App或网站收集使用处理个人信息",
        "text": "###  一、我们如何收集和使用您的个人信息",
        "start": 525,
        "end": 547,
        "fields": [],
        "sub_annotations": []
    },
    {
        "classId": "e_1",
        "classId_name": "App或网站收集使用处理个人信息",
        "text": "（二）在您使用服务过程中收集的信息\n为了提供并优化您需要的服务，我们会在搜集个人信息前在征得您的同意，且所收集的信息不会超出必要信息范围，收集您使用服务的相关信息包括： 2.1\n我们会在根据您在软件安装及使用汇总授予的具体权限，接收并记录您所使用的智能设备相关信息，包括设备型号、操作系统版本、设备设置、设备唯一标识字符等软硬件特征信息，您对软硬件的使用记录、软硬件故障信息数据，包括但不限于您的IP地址、访问日期和时间、语言、软硬件特征信息、地理位置；如您下载或使用格力或其关联公司客户端软件，格力可能会读取与您位置和移动设备相关的信息，包括但不限于设备型号、操作系统、设备识别码、分辨率、电信运营商。\n2.2\n除上述信息外，我们还可能为了提供服务及改进服务质量、服务个性化等合理需要而收集您的其他信息，包括但不限于您与我们的客户服务团队联系时您提供的相关信息，您参与问卷调查活动时向我们提供的问卷答复信息，以及您与格力的关联方、合作伙伴之间互动时我们收集的相关信息。与此同时，为提高您使用格力平台服务时的安全性，预防钓鱼网站欺诈和木马病毒，我们可能会通过了解或记录一些您的网络使用习惯、您常用的软件信息等手段来判断您账户的风险，并可能会记录一些我们认为有风险的URL。\n以下为相关应用场景/业务功能及影响： 家庭管理：根据用户信息进行家庭成员邀请； 服务预约：根据用户填写的信息提供相关保养、投诉、咨询、报修、报装、移机服务；\n附近门店：根据用户定位判断该地区门店位置； 下单：用于生成订单时，显示订单中的物流信息并同步物流配送； 库存：根据用户定位判断该地区商品储货情况。\n涉及的各项业务功能实际收集的个人信息类型与隐私政策所描述内容一致，且不会超出隐私政策所述范围。",
        "start": 920,
        "end": 1657,
        "fields": [],
        "sub_annotations": []
    },
    {
        "classId": "e_1",
        "classId_name": "App或网站收集使用处理个人信息",
        "text": "（三）我们还可能收集其他无法识别到特定个人的信息（即不属于个人信息的信息），例如您使用特定服务时产生的统计类数据，如用户的操作行为（包括点击、页面跳转、浏览时间）。收集此类信息的目的在于改善我们向您提供的服务。所收集信息的类别和数量取决于您如何使用我们产品和/或服务。\n我们会将此类信息汇总，用于帮助我们向客户提供更有用的信息，了解客户对我们网站、产品和服务中的哪些部分最感兴趣。就本隐私政策而言，汇总数据被视为非个人信息。如果我们将非个人信息与个人信息结合使用，则在结合使用期间，此类信息将被视为个人信息。",
        "start": 1669,
        "end": 1923,
        "fields": [],
        "sub_annotations": []
    },
    {
        "classId": "e_1",
        "classId_name": "App或网站收集使用处理个人信息",
        "text": "（四）您充分知晓，以下情形中，我们收集、使用个人信息或非个人信息无需征得您的同意：\n4.1 与国家安全、国防安全有关的； 4.2 与公共安全、公共卫生、重大公共利益有关的； 4.3 与犯罪侦查、起诉、审判和判决执行等有关的； 4.4\n出于维护个人信息主体或其他个人的生命、财产等重大合法权益但又很难得到本人同意的； 4.5 所收集的个人信息是个人信息主体自行向社会公众公开的； 4.6\n从合法公开披露的信息中收集的您的个人信息的，如合法的新闻报道、政府信息公开等渠道； 4.7 根据您的要求签订合同所必需的； 4.8\n用于维护所提供的产品与/或服务的安全稳定运行所必需的，例如发现、处置产品与/或服务的故障； 4.9 为合法的新闻报道所必需的；",
        "start": 1935,
        "end": 2257,
        "fields": [],
        "sub_annotations": []
    },
    {
        "classId": "e_8",
        "classId_name": "信息定义",
        "text": "个人信息是指以电子或者其他方式记录的能够单独或者与其他信息结合识别特定自然人身份或者反映特定自然人活动情况的各种信息。格力仅会出于本政策所述的以下目的，收集和使用您的个人信息",
        "start": 548,
        "end": 635,
        "fields": [],
        "sub_annotations": []
    },
    {
        "classId": "e_3",
        "classId_name": "用户提供个人信息",
        "text": "（一）您向我们提供的信息\n当您注册格力账户及您在使用格力平台时提供的相关服务时填写及/或提交的信息，包括您的姓名、性别、出生年月日、身份证号码、护照姓名、护照号码、电话号码、电子邮箱、地址、邮编、银行账号、收件信息和相关附加信息。\n格力+将通过格力+页面向您展示需要您提交的信息，届时以页面展示为准，如果您不使用某些服务，则无需提供相关信息。对于您明确拒绝使用、关闭或退出的特定业务功能，App在您打开该业务功能或相关系统权限时将会再次询问您是否您是否同意开启相关权限，且App在更新升级后，不会更改原有的系统权限设置。",
        "start": 648,
        "end": 908,
        "fields": [],
        "sub_annotations": []
    },
    {
        "classId": "e_24",
        "classId_name": "操作者",
        "text": "您",
        "start": 662,
        "end": 663,
        "fields": [],
        "sub_annotations": []
    },
    {
        "classId": "e_24",
        "classId_name": "操作者",
        "text": "您",
        "start": 670,
        "end": 671,
        "fields": [],
        "sub_annotations": []
    },
    {
        "classId": "e_24",
        "classId_name": "操作者",
        "text": "我们",
        "start": 952,
        "end": 954,
        "fields": [],
        "sub_annotations": []
    },
    {
        "classId": "e_24",
        "classId_name": "操作者",
        "text": "我们",
        "start": 1009,
        "end": 1011,
        "fields": [],
        "sub_annotations": []
    },
    {
        "classId": "e_24",
        "classId_name": "操作者",
        "text": "格力",
        "start": 1168,
        "end": 1170,
        "fields": [],
        "sub_annotations": []
    },
    {
        "classId": "e_24",
        "classId_name": "操作者",
        "text": "我们",
        "start": 1672,
        "end": 1674,
        "fields": [],
        "sub_annotations": []
    },
    {
        "classId": "e_24",
        "classId_name": "操作者",
        "text": "我们",
        "start": 2302,
        "end": 2304,
        "fields": [],
        "sub_annotations": []
    },
    {
        "classId": "e_24",
        "classId_name": "操作者",
        "text": "我们",
        "start": 2366,
        "end": 2368,
        "fields": [],
        "sub_annotations": []
    },
    {
        "classId": "e_24",
        "classId_name": "操作者",
        "text": "我们",
        "start": 2385,
        "end": 2387,
        "fields": [],
        "sub_annotations": []
    },
    {
        "classId": "e_24",
        "classId_name": "操作者",
        "text": "我们",
        "start": 2459,
        "end": 2461,
        "fields": [],
        "sub_annotations": []
    },
    {
        "classId": "e_24",
        "classId_name": "操作者",
        "text": "我们",
        "start": 2565,
        "end": 2567,
        "fields": [],
        "sub_annotations": []
    },
    {
        "classId": "e_24",
        "classId_name": "操作者",
        "text": "我们",
        "start": 2618,
        "end": 2620,
        "fields": [],
        "sub_annotations": []
    },
    {
        "classId": "e_24",
        "classId_name": "操作者",
        "text": "我们",
        "start": 2658,
        "end": 2660,
        "fields": [],
        "sub_annotations": []
    },
    {
        "classId": "e_24",
        "classId_name": "操作者",
        "text": "我们",
        "start": 2830,
        "end": 2832,
        "fields": [],
        "sub_annotations": []
    },
    {
        "classId": "e_24",
        "classId_name": "操作者",
        "text": "我们",
        "start": 2890,
        "end": 2892,
        "fields": [],
        "sub_annotations": []
    },
    {
        "classId": "e_24",
        "classId_name": "操作者",
        "text": "我们",
        "start": 3012,
        "end": 3014,
        "fields": [],
        "sub_annotations": []
    },
    {
        "classId": "e_24",
        "classId_name": "操作者",
        "text": "我们",
        "start": 3085,
        "end": 3087,
        "fields": [],
        "sub_annotations": []
    },
    {
        "classId": "e_24",
        "classId_name": "操作者",
        "text": "我们",
        "start": 3446,
        "end": 3448,
        "fields": [],
        "sub_annotations": []
    },
    {
        "classId": "e_25",
        "classId_name": "条件",
        "text": "注册格力账户",
        "start": 663,
        "end": 669,
        "fields": [],
        "sub_annotations": []
    },
    {
        "classId": "e_25",
        "classId_name": "条件",
        "text": "在使用格力平台时提供的相关服务时",
        "start": 671,
        "end": 687,
        "fields": [],
        "sub_annotations": []
    },
    {
        "classId": "e_25",
        "classId_name": "条件",
        "text": "征得您的同意",
        "start": 964,
        "end": 970,
        "fields": [],
        "sub_annotations": []
    },
    {
        "classId": "e_25",
        "classId_name": "条件",
        "text": "根据您在软件安装及使用汇总授予的具体权限",
        "start": 1013,
        "end": 1033,
        "fields": [],
        "sub_annotations": []
    },
    {
        "classId": "e_25",
        "classId_name": "条件",
        "text": "如您下载或使用格力或其关联公司客户端软件",
        "start": 1147,
        "end": 1167,
        "fields": [],
        "sub_annotations": []
    },
    {
        "classId": "e_25",
        "classId_name": "条件",
        "text": "但以下情况除外",
        "start": 2331,
        "end": 2338,
        "fields": [],
        "sub_annotations": []
    },
    {
        "classId": "e_25",
        "classId_name": "条件",
        "text": "获得您的明确同意后",
        "start": 2356,
        "end": 2365,
        "fields": [],
        "sub_annotations": []
    },
    {
        "classId": "e_25",
        "classId_name": "条件",
        "text": "根据法律法规规定",
        "start": 2390,
        "end": 2398,
        "fields": [],
        "sub_annotations": []
    },
    {
        "classId": "e_25",
        "classId_name": "条件",
        "text": "按政府主管部门的强制性要求",
        "start": 2400,
        "end": 2413,
        "fields": [],
        "sub_annotations": []
    },
    {
        "classId": "e_25",
        "classId_name": "条件",
        "text": "受本隐私政策中所声明目的的约束",
        "start": 2474,
        "end": 2489,
        "fields": [],
        "sub_annotations": []
    },
    {
        "classId": "e_25",
        "classId_name": "条件",
        "text": "在您上网购买我们的产品时",
        "start": 2605,
        "end": 2617,
        "fields": [],
        "sub_annotations": []
    },
    {
        "classId": "e_25",
        "classId_name": "条件",
        "text": "但以下情况除外",
        "start": 2855,
        "end": 2862,
        "fields": [],
        "sub_annotations": []
    },
    {
        "classId": "e_25",
        "classId_name": "条件",
        "text": "获得您的明确同意后",
        "start": 2880,
        "end": 2889,
        "fields": [],
        "sub_annotations": []
    },
    {
        "classId": "e_25",
        "classId_name": "条件",
        "text": "在以下情况下",
        "start": 3016,
        "end": 3022,
        "fields": [],
        "sub_annotations": []
    },
    {
        "classId": "e_25",
        "classId_name": "条件",
        "text": "在法律、法律程序、诉讼或政府主管部门强制性要求的情况下",
        "start": 3057,
        "end": 3084,
        "fields": [],
        "sub_annotations": []
    },
    {
        "classId": "e_25",
        "classId_name": "条件",
        "text": "在达成本政策所述目的所需的期限内",
        "start": 3450,
        "end": 3466,
        "fields": [],
        "sub_annotations": []
    },
    {
        "classId": "e_25",
        "classId_name": "条件",
        "text": "除非需要延长保留期",
        "start": 3475,
        "end": 3484,
        "fields": [],
        "sub_annotations": []
    },
    {
        "classId": "e_25",
        "classId_name": "条件",
        "text": "受到法律的允许",
        "start": 3485,
        "end": 3492,
        "fields": [],
        "sub_annotations": []
    },
    {
        "classId": "e_23",
        "classId_name": "分享",
        "text": "填写",
        "start": 687,
        "end": 689,
        "fields": [],
        "sub_annotations": []
    },
    {
        "classId": "e_23",
        "classId_name": "分享",
        "text": "提交",
        "start": 692,
        "end": 694,
        "fields": [],
        "sub_annotations": []
    },
    {
        "classId": "e_23",
        "classId_name": "分享",
        "text": "分享",
        "start": 2322,
        "end": 2324,
        "fields": [],
        "sub_annotations": []
    },
    {
        "classId": "e_23",
        "classId_name": "分享",
        "text": "共享",
        "start": 2373,
        "end": 2375,
        "fields": [],
        "sub_annotations": []
    },
    {
        "classId": "e_23",
        "classId_name": "分享",
        "text": "共享",
        "start": 2416,
        "end": 2418,
        "fields": [],
        "sub_annotations": []
    },
    {
        "classId": "e_23",
        "classId_name": "分享",
        "text": "共享",
        "start": 2463,
        "end": 2465,
        "fields": [],
        "sub_annotations": []
    },
    {
        "classId": "e_23",
        "classId_name": "分享",
        "text": "共享",
        "start": 2575,
        "end": 2577,
        "fields": [],
        "sub_annotations": []
    },
    {
        "classId": "e_23",
        "classId_name": "分享",
        "text": "共享",
        "start": 2630,
        "end": 2632,
        "fields": [],
        "sub_annotations": []
    },
    {
        "classId": "e_23",
        "classId_name": "分享",
        "text": "共享",
        "start": 2681,
        "end": 2683,
        "fields": [],
        "sub_annotations": []
    },
    {
        "classId": "e_23",
        "classId_name": "分享",
        "text": "共享",
        "start": 2694,
        "end": 2696,
        "fields": [],
        "sub_annotations": []
    },
    {
        "classId": "e_23",
        "classId_name": "分享",
        "text": "转让",
        "start": 2841,
        "end": 2843,
        "fields": [],
        "sub_annotations": []
    },
    {
        "classId": "e_23",
        "classId_name": "分享",
        "text": "转让",
        "start": 2897,
        "end": 2899,
        "fields": [],
        "sub_annotations": []
    },
    {
        "classId": "e_23",
        "classId_name": "分享",
        "text": "公开披露",
        "start": 3023,
        "end": 3027,
        "fields": [],
        "sub_annotations": []
    },
    {
        "classId": "e_23",
        "classId_name": "分享",
        "text": "公开披露",
        "start": 3090,
        "end": 3094,
        "fields": [],
        "sub_annotations": []
    },
    {
        "classId": "e_21",
        "classId_name": "数据",
        "text": "姓名、性别、出生年月日、身份证号码、护照姓名、护照号码、电话号码、电子邮箱、地址、邮编、银行账号、收件信息",
        "start": 702,
        "end": 755,
        "fields": [],
        "sub_annotations": []
    },
    {
        "classId": "e_21",
        "classId_name": "数据",
        "text": "个人信息",
        "start": 958,
        "end": 962,
        "fields": [],
        "sub_annotations": []
    },
    {
        "classId": "e_21",
        "classId_name": "数据",
        "text": "智能设备相关信息",
        "start": 1044,
        "end": 1052,
        "fields": [],
        "sub_annotations": []
    },
    {
        "classId": "e_21",
        "classId_name": "数据",
        "text": "设备型号、操作系统版本、设备设置、设备唯一标识字符等软硬件特征信息",
        "start": 1055,
        "end": 1088,
        "fields": [],
        "sub_annotations": []
    },
    {
        "classId": "e_21",
        "classId_name": "数据",
        "text": "软硬件的使用记录",
        "start": 1091,
        "end": 1099,
        "fields": [],
        "sub_annotations": []
    },
    {
        "classId": "e_21",
        "classId_name": "数据",
        "text": "软硬件故障信息数据",
        "start": 1100,
        "end": 1109,
        "fields": [],
        "sub_annotations": []
    },
    {
        "classId": "e_21",
        "classId_name": "数据",
        "text": "IP地址、访问日期和时间、语言、软硬件特征信息、地理位置",
        "start": 1118,
        "end": 1146,
        "fields": [],
        "sub_annotations": []
    },
    {
        "classId": "e_21",
        "classId_name": "数据",
        "text": "您位置和移动设备相关的信息",
        "start": 1176,
        "end": 1189,
        "fields": [],
        "sub_annotations": []
    },
    {
        "classId": "e_21",
        "classId_name": "数据",
        "text": "设备型号、操作系统、设备识别码、分辨率、电信运营商",
        "start": 1196,
        "end": 1221,
        "fields": [],
        "sub_annotations": []
    },
    {
        "classId": "e_21",
        "classId_name": "数据",
        "text": "无法识别到特定个人的信息",
        "start": 1681,
        "end": 1693,
        "fields": [],
        "sub_annotations": []
    },
    {
        "classId": "e_21",
        "classId_name": "数据",
        "text": "统计类数据",
        "start": 1720,
        "end": 1725,
        "fields": [],
        "sub_annotations": []
    },
    {
        "classId": "e_21",
        "classId_name": "数据",
        "text": "用户的操作行为",
        "start": 1727,
        "end": 1734,
        "fields": [],
        "sub_annotations": []
    },
    {
        "classId": "e_21",
        "classId_name": "数据",
        "text": "点击、页面跳转、浏览时间",
        "start": 1737,
        "end": 1749,
        "fields": [],
        "sub_annotations": []
    },
    {
        "classId": "e_21",
        "classId_name": "数据",
        "text": "个人信息",
        "start": 2326,
        "end": 2330,
        "fields": [],
        "sub_annotations": []
    },
    {
        "classId": "e_21",
        "classId_name": "数据",
        "text": "个人信息",
        "start": 2377,
        "end": 2381,
        "fields": [],
        "sub_annotations": []
    },
    {
        "classId": "e_21",
        "classId_name": "数据",
        "text": "个人信息",
        "start": 2420,
        "end": 2424,
        "fields": [],
        "sub_annotations": []
    },
    {
        "classId": "e_21",
        "classId_name": "数据",
        "text": "个人信息",
        "start": 2468,
        "end": 2472,
        "fields": [],
        "sub_annotations": []
    },
    {
        "classId": "e_21",
        "classId_name": "数据",
        "text": "个人信息",
        "start": 2581,
        "end": 2585,
        "fields": [],
        "sub_annotations": []
    },
    {
        "classId": "e_21",
        "classId_name": "数据",
        "text": "个人信息",
        "start": 2634,
        "end": 2638,
        "fields": [],
        "sub_annotations": []
    },
    {
        "classId": "e_21",
        "classId_name": "数据",
        "text": "个人信息",
        "start": 2685,
        "end": 2689,
        "fields": [],
        "sub_annotations": []
    },
    {
        "classId": "e_21",
        "classId_name": "数据",
        "text": "个人信息",
        "start": 2704,
        "end": 2708,
        "fields": [],
        "sub_annotations": []
    },
    {
        "classId": "e_21",
        "classId_name": "数据",
        "text": "个人信息",
        "start": 2837,
        "end": 2841,
        "fields": [],
        "sub_annotations": []
    },
    {
        "classId": "e_21",
        "classId_name": "数据",
        "text": "个人信息",
        "start": 2901,
        "end": 2905,
        "fields": [],
        "sub_annotations": []
    },
    {
        "classId": "e_21",
        "classId_name": "数据",
        "text": "个人信息",
        "start": 3029,
        "end": 3033,
        "fields": [],
        "sub_annotations": []
    },
    {
        "classId": "e_21",
        "classId_name": "数据",
        "text": "个人信息",
        "start": 3096,
        "end": 3100,
        "fields": [],
        "sub_annotations": []
    },
    {
        "classId": "e_21",
        "classId_name": "数据",
        "text": "个人信息",
        "start": 3470,
        "end": 3474,
        "fields": [],
        "sub_annotations": []
    },
    {
        "classId": "e_27",
        "classId_name": "目的",
        "text": "为了提供并优化您需要的服务",
        "start": 938,
        "end": 951,
        "fields": [],
        "sub_annotations": []
    },
    {
        "classId": "e_27",
        "classId_name": "目的",
        "text": "以提供更好的客户服务和用户体验",
        "start": 2586,
        "end": 2601,
        "fields": [],
        "sub_annotations": []
    },
    {
        "classId": "e_27",
        "classId_name": "目的",
        "text": "才能安排送货",
        "start": 2638,
        "end": 2644,
        "fields": [],
        "sub_annotations": []
    },
    {
        "classId": "e_27",
        "classId_name": "目的",
        "text": "安排合作伙伴提供服务",
        "start": 2647,
        "end": 2657,
        "fields": [],
        "sub_annotations": []
    },
    {
        "classId": "e_27",
        "classId_name": "目的",
        "text": "出于合法、正当、必要、特定、明确的目的",
        "start": 2662,
        "end": 2681,
        "fields": [],
        "sub_annotations": []
    },
    {
        "classId": "e_22",
        "classId_name": "收集",
        "text": "搜集",
        "start": 956,
        "end": 958,
        "fields": [],
        "sub_annotations": []
    },
    {
        "classId": "e_22",
        "classId_name": "收集",
        "text": "接收",
        "start": 1034,
        "end": 1036,
        "fields": [],
        "sub_annotations": []
    },
    {
        "classId": "e_22",
        "classId_name": "收集",
        "text": "记录",
        "start": 1037,
        "end": 1039,
        "fields": [],
        "sub_annotations": []
    },
    {
        "classId": "e_22",
        "classId_name": "收集",
        "text": "读取",
        "start": 1173,
        "end": 1175,
        "fields": [],
        "sub_annotations": []
    },
    {
        "classId": "e_22",
        "classId_name": "收集",
        "text": "收集",
        "start": 1677,
        "end": 1679,
        "fields": [],
        "sub_annotations": []
    },
    {
        "classId": "e_22",
        "classId_name": "收集",
        "text": "保留",
        "start": 3466,
        "end": 3468,
        "fields": [],
        "sub_annotations": []
    },
    {
        "classId": "e_2",
        "classId_name": "第三方收集或共享个人信息",
        "text": "### 二、我们如何共享、转让、公开披露您的个人信息\n（一）共享\n我们不会与格力以外的任何公司、组织和个人分享您的个人信息，但以下情况除外：\n1、在获取明确同意的情况下共享：获得您的明确同意后，我们会与其他方共享您的个人信息。\n2、我们可能会根据法律法规规定，或按政府主管部门的强制性要求，对外共享您的个人信息。\n3、与我们的关联公司共享：您的个人信息可能会与格力的关联公司共享。我们只会共享必要的个人信息，且受本隐私政策中所声明目的的约束。附属公司如要改变个人信息的处理目的，将再次征求您的授权同意。\n4、与授权合作伙伴共享：仅为实现本政策中声明的目的，我们的某些服务将由授权合作伙伴提供。我们可能会与合作伙伴共享您的某些个人信息，以提供更好的客户服务和用户体验。例如，在您上网购买我们的产品时，我们必须与物流服务提供商共享您的个人信息才能安排送货，或者安排合作伙伴提供服务。我们仅会出于合法、正当、必要、特定、明确的目的共享您的个人信息，并且只会共享提供服务所必要的个人信息。我们的合作伙伴无权将共享的个人信息用于任何其他用途。对我们与之共享个人信息的公司、组织和个人，我们会与其签署严格的保密协定，要求他们按照我们的说明、本隐私政策以及其他任何相关的保密和安全措施来处理个人信息。",
        "start": 2269,
        "end": 2812,
        "fields": [],
        "sub_annotations": []
    },
    {
        "classId": "e_2",
        "classId_name": "第三方收集或共享个人信息",
        "text": "（二）转让\n我们不会将您的个人信息转让给任何公司、组织和个人，但以下情况除外： 1、在获取明确同意的情况下转让：获得您的明确同意后，我们会向其他方转让您的个人信息。\n2、在涉及合并、收购或破产清算时，如涉及到个人信息转让，我们会在要求新的持有您个人信息的公司、组织继续受此隐私政策的约束，否则我们将要求该公司、组织重新向您征求授权同意。",
        "start": 2824,
        "end": 2992,
        "fields": [],
        "sub_annotations": []
    },
    {
        "classId": "e_2",
        "classId_name": "第三方收集或共享个人信息",
        "text": "（三）公开披露\n我们仅会在以下情况下，公开披露您的个人信息： 1、获得您明确同意后。\n2、基于法律的披露：在法律、法律程序、诉讼或政府主管部门强制性要求的情况下，我们可能会公开披露您的个人信息。",
        "start": 3004,
        "end": 3101,
        "fields": [],
        "sub_annotations": []
    },
    {
        "classId": "e_26",
        "classId_name": "受试者",
        "text": "格力以外的任何公司、组织和个人",
        "start": 2307,
        "end": 2322,
        "fields": [],
        "sub_annotations": []
    },
    {
        "classId": "e_26",
        "classId_name": "受试者",
        "text": "其他方",
        "start": 2370,
        "end": 2373,
        "fields": [],
        "sub_annotations": []
    },
    {
        "classId": "e_26",
        "classId_name": "受试者",
        "text": "合作伙伴",
        "start": 2571,
        "end": 2575,
        "fields": [],
        "sub_annotations": []
    },
    {
        "classId": "e_26",
        "classId_name": "受试者",
        "text": "物流服务提供商",
        "start": 2623,
        "end": 2630,
        "fields": [],
        "sub_annotations": []
    },
    {
        "classId": "e_26",
        "classId_name": "受试者",
        "text": "任何公司、组织和个人",
        "start": 2844,
        "end": 2854,
        "fields": [],
        "sub_annotations": []
    },
    {
        "classId": "e_26",
        "classId_name": "受试者",
        "text": "其他方",
        "start": 2894,
        "end": 2897,
        "fields": [],
        "sub_annotations": []
    },
    {
        "classId": "e_6",
        "classId_name": "数据安全",
        "text": "###  三、我们如何保护您的个人信息\n（一）我们保护您的个人信息的技术与措施\n我们非常重视个人信息安全，并采取一切合理可行的措施，保护您的个人信息： \n1\\. 数据安全技术措施\n我们已使用符合业界标准的安全防护措施保护您提供的个人信息，防止数据遭到未经授权访问、公开披露、使用、修改、损坏或丢失。我们会采取一切合理可行的措施，保护您的个人信息。我们会使用加密技术提高用户信息的安全性；我们会使用受信赖的保护机制防止用户信息遭到恶意代码攻击；例如，在您的浏览器与“服务”之间交换数据（如信用卡信息）时受SSL 加密保护；我们会部署访问控制机制，确保只有授权人员才可访问个人信息； \n2\\. 其他安全措施 2.1我们会采取一切合理可行的措施，确保未收集无关的个人信息。我们只会在达成本政策所述目的所需的期限内保留您的个人信息，除非需要延长保留期或受到法律的允许。\n2.2 格力+智能产品通过建立数据分类分级制度、数据安全管理规范、数据安全开发规范来管理规范个人信息的存储和使用。 \n2.3格力+智能产品通过信息接触者保密协议、监控和审计机制来对数据进行全面安全控制。 \n2.4格力+智能产品建立数据安全委员会并下设信息保护专职部门、数据安全应急响应组织来推进和保障个人信息安全。 \n2.5加强安全意识。我们还会举办安全和隐私保护培训课程，加强员工对于保护个人信息重要性的认识。 \n2.6我们仅允许有必要知晓这些信息的格力+智能产品及格力+智能产品关联方的员工、合作伙伴访问个人信息，并为此设置了严格的访问权限控制和监控机制。我们同时要求可能接触到您个人信息的所有人员履行相应的保密义务。如果未能履行这些义务，可能会被追究法律责任或被中止与格力+的合作关系。我们同时要求可能接触到您个人信息的所有人员履行相应的保密义务。如果未能履行这些义务，可能会被追究法律责任或被中止与格力的合作关系。\n3\\.互联网并非绝对安全的环境，而且电子邮件、即时通讯、及与其他格力+App用户的交流方式并未加密，我们强烈建议您不要通过此类方式发送个人信息。请使用复杂密码，协助我们保证您的账号安全。\n4\\. 互联网环境并非百分之百安全，我们将尽力确保或担保您发送给我们的任何信息的安全性。 5\\.\n在不幸发生个人信息安全事件后，我们将按照法律法规的要求，及时向您告知：安全事件的基本情况和可能的影响、我们已采取或将要采取的处置措施、您可自主防范和降低风险的建议、对您的补救措施等。我们将及时将事件相关情况以邮件、信函、电话、推送通知等方式告知您，难以逐一告知个人信息主体时，我们会采取合理、有效的方式发布公告。同时，我们还将按照监管部门要求，主动上报个人信息安全事件的处置情况。\n6\\.为应对个人信息泄露、损毁和丢失等可能出现的风险，格力+智能产品制定了多项制度，明确安全事件、安全漏洞的分类分级标准及相应的处理流程。我们也为安全事件建立了专门的应急响应团队，按照安全事件处置规范要求，针对不同安全事件启动安全预案，进行止损、分析、定位、制定补救措施、联合相关部门进行溯源和打击。\n7\\.如果您对我们的个人信息保护有任何疑问，可通过本隐私政策最下方约定的联系方式联系我们。您发现自己的个人信息泄密，尤其是您的账户及密码发生泄露，请您立即通过本隐私政策最下方【如何联系我们】约定的联系方式联络我们，以便我们采取相应措施。",
        "start": 3113,
        "end": 4509,
        "fields": [],
        "sub_annotations": []
    },
    {
        "classId": "e_11",
        "classId_name": "年龄限制条款",
        "text": "### 四、我们如何处理儿童的个人信息\n我们的产品、网站和服务主要面向成人。如果没有父母或监护人的同意，儿童不得创建自己的用户账户。对于经父母同意而收集儿童个人信息的情况，我们只会在受到法律允许、父母或监护人明确同意或者保护儿童所必要的情况下使用或公开披露此信息。尽管当地法律和习俗对儿童的定义不同，但我们将不满\n14 周岁的任何人均视为儿童。如果我们发现自己在未事先获得可证实的父母同意的情况下收集了儿童的个人信息，则会设法尽快删除相关数据。\n针对儿童使用格力+产品及服务，我们特别制定了[《格力+儿童个人信息保护规则及监护人须知》](./childProtectRules.html)，请您仔细阅读，并在充分理解并同意后使用我们的产品及服务。",
        "start": 4521,
        "end": 4844,
        "fields": [],
        "sub_annotations": []
    },
    {
        "classId": "e_15",
        "classId_name": "网站Cookie及WebBeacon使用",
        "text": "### 五、我们如何使用 Cookie 和同类技术\n（一）Cookie\n为确保网站正常运转，我们会在您的计算机或移动设备上存储名为Cookie的小数据文件。Cookie通常包含标识符、站点名称以及一些号码和字符。借助于Cookie，设备能够存储您的偏好或使用的智能产品数据。我们不会将Cookie用于本政策所述目的(分享/第三方登录)之外的任何用途。您可根据自己的偏好管理或删除 Cookie。您可以清除设备上保存的所有Cookie，但如果您这么做，则需要在每一次访问我们的时候更改用户设置。除Cookie外，我们还会在上使用信标和像素标签技术。我们不存在嵌入第三方代码插件收集个人信息的功能。\n大部分网络浏览器都设有阻止Cookie的功能。但如果您这么做，则需要在每一次访问我们的网站时亲自更改用户设置。\n（二）网站信标和像素标签\n除 Cookie外，我们还会在网站上使用网站信标和像素标签等其他同类技术。例如，我们向您发送的电子邮件可能含有链接至我们网站内容的点击URL。如果您点击该链接，我们则会跟踪此次点击，帮助我们了解您的产品或服务偏好并改善客户服务。网站信标通常是一种嵌入到网站或电子邮件中的透明图像。借助于电子邮件中的像素标签，我们能够获知电子邮件是否被打开。如果您不希望自己的活动以这种方式被追踪，则可以随时从我们的寄信名单中退订。\n（三）Do Not Track（请勿追踪）\n很多网络浏览器均设有 Do Not Track功能，该功能可向网站发布 Do Not Track请求。目前，主要互联网标准组织尚未设立相关政策来规定网站应如何应对此类请求。但如果您的浏览器启用了 Do Not Track，那么我们的所有网站都会尊重您的选择。",
        "start": 4856,
        "end": 5582,
        "fields": [],
        "sub_annotations": []
    },
    {
        "classId": "e_4",
        "classId_name": "用户权利增删改查",
        "text": "### 六、您的权利\n按照中国相关的法律、法规、标准，以及其他国家、地区的通行做法，我们保障您对自己的个人信息行使以下权利： \n（一）访问您的个人信息\n您有权访问您的个人信息，法律法规规定的例外情况除外。如果您想行使数据访问权，可以通过以下方式自行访问：\n账户信息——如果您希望访问或编辑您的账户中的个人资料信息和支付信息、更改您的密码、添加安全信息或关闭您的账户等，您可以通过访问格力+App执行此类操作。如果您无法通过上述链接访问这些个人信息，您可以通过发送电子邮件sale@cn.gree.com或传真0756-8614998的方式提出访问请求，我们将在15天内回复您的访问请求。\n对于您在使用我们的产品或服务过程中产生的其他个人信息，只要我们不需要过多投入，我们会向您提供。 \n（二）更正您的个人信息\n当您发现我们处理的关于您的个人信息有错误时，您有权要求我们做出更正。您可以通过“（一）访问您的个人信息”中罗列的方式提出更正申请。如果您无法通过上述链接更正这些个人信息，您可以随时使用格力+App反馈问题给我们，或发送电子邮件至格力。我们将在15天内回复您的更正请求。",
        "start": 5594,
        "end": 6083,
        "fields": [],
        "sub_annotations": []
    },
    {
        "classId": "e_4",
        "classId_name": "用户权利增删改查",
        "text": "（四）响应您的上述请求\n为保障安全，您可能需要提供书面请求，或以其他方式证明您的身份。我们可能会先要求您验证自己的身份，然后再处理您的请求。我们将在15天内做出答复。如您不满意，还可以联系客服投诉。\n对于您合理的请求，我们原则上不收取费用，但对多次重复、超出合理限度的请求，我们将视情收取一定成本费用。对于那些无端重复、需要过多技术手段（例如，需要开发新系统或从根本上改变现行惯例）、给他人合法权益带来风险或者非常不切实际（例如，涉及备份磁带上存放的信息）的请求，我们可能会予以拒绝。\n在以下情形中，按照法律法规要求，我们将无法响应您的请求： 1、与国家安全、国防安全直接相关的。 2、与公共安全、公共卫生、重大公共利益直接相关的。\n3、与犯罪侦查、起诉、审判和判决执行等直接相关的。 4、有充分证据表明您存在主观恶意或滥用权利的。\n5、响应您的请求将导致您或其他个人、组织的合法权益受到严重损害的。 6、涉及商业秘密的。",
        "start": 6248,
        "end": 6659,
        "fields": [],
        "sub_annotations": []
    },
    {
        "classId": "e_9",
        "classId_name": "获取撤回同意",
        "text": "（三）改变您授权同意的范围\n每个业务功能需要一些基本的个人信息才能得以完成（见本政策“第一部分”）。对于额外收集的个人信息的收集和使用，您可以随时给予或收回您的授权同意。当您收回同意后，我们将不再处理相应的个人信息。但您收回同意的决定，不会影响此前基于您的授权而开展的个人信息处理。",
        "start": 6095,
        "end": 6236,
        "fields": [],
        "sub_annotations": []
    },
    {
        "classId": "e_5",
        "classId_name": "数据保存",
        "text": "### 七、您的个人信息如何储存及超出储存期限处理办法\n我们在中华人民共和国境内收集和产生的个人信息，将存储在中华人民共和国境内。对于您个人信息的存储期限将依照法律最短期限进行处理。",
        "start": 6671,
        "end": 6762,
        "fields": [],
        "sub_annotations": []
    },
    {
        "classId": "e_7",
        "classId_name": "隐私政策修改更新",
        "text": "### 八、本政策如何更新\n我们的隐私政策可能变更。未经您明确同意，我们不会削减您按照本隐私政策所应享有的权利。我们会在本页面上发布对本政策所做的任何变更。对于重大变更，我们还会提供更为显著的通知（包括对于某些服务，我们会通过电子邮件发送通知，说明隐私政策的具体变更内容）。\n本政策所指的重大变更包括但不限于： 1、我们的服务模式发生重大变化。如处理个人信息的目的、处理的个人信息类型、个人信息的使用方式等。\n2、我们在所有权结构、组织架构等方面发生重大变化。如业务调整、破产并购等引起的所有者变更等。 \n3、个人信息共享、转让或公开披露的主要对象发生变化。\n4、您参与个人信息处理方面的权利及其行使方式发生重大变化。 \n5、我们负责处理个人信息安全的责任部门、联络方式及投诉渠道发生变化时。\n6、个人信息安全影响评估报告表明存在高风险时。我们还会将本政策的旧版本存档，供您查阅。",
        "start": 6774,
        "end": 7164,
        "fields": [],
        "sub_annotations": []
    },
    {
        "classId": "e_14",
        "classId_name": "开发者公司名称联系方式",
        "text": "### 九、如何联系我们\n如果您对本隐私政策有任何疑问、意见或建议，您可以通过如下方式与我们取得联系： 电子邮件：sale@cn.gree.com 电 话：4008365315 传\n真：0756-8614998 注册地址：广东省珠海市前山金鸡西路6号\n我们设立了个人信息保护专职部门，一般情况下，我们将在15天内回复。如果您对我们的回复不满意，特别是我们的个人信息处理行为损害了您的合法权益，您还可以通过上述途径寻求解决方案。",
        "start": 7176,
        "end": 7389,
        "fields": [],
        "sub_annotations": []
    }
]